pulumi_openstack/__init__.py
pulumi_openstack/_inputs.py
pulumi_openstack/_utilities.py
pulumi_openstack/bgpvpn_network_associate_v2.py
pulumi_openstack/bgpvpn_port_associate_v2.py
pulumi_openstack/bgpvpn_router_associate_v2.py
pulumi_openstack/bgpvpn_v2.py
pulumi_openstack/get_fw_group_v2.py
pulumi_openstack/get_fw_policy_v2.py
pulumi_openstack/get_fw_rule_v2.py
pulumi_openstack/lb_flavorprofile_v2.py
pulumi_openstack/lb_loadbalancer_v2.py
pulumi_openstack/outputs.py
pulumi_openstack/provider.py
pulumi_openstack/pulumi-plugin.json
pulumi_openstack/py.typed
pulumi_openstack/taas_tap_mirror_v2.py
pulumi_openstack/workflow_workflow_v2.py
pulumi_openstack/bgpvpn/__init__.py
pulumi_openstack/bgpvpn/_inputs.py
pulumi_openstack/bgpvpn/network_associate_v2.py
pulumi_openstack/bgpvpn/outputs.py
pulumi_openstack/bgpvpn/port_associate_v2.py
pulumi_openstack/bgpvpn/router_associate_v2.py
pulumi_openstack/bgpvpn/v2.py
pulumi_openstack/blockstorage/__init__.py
pulumi_openstack/blockstorage/_inputs.py
pulumi_openstack/blockstorage/get_availability_zones_v3.py
pulumi_openstack/blockstorage/get_quotaset_v3.py
pulumi_openstack/blockstorage/get_snapshot_v3.py
pulumi_openstack/blockstorage/get_volume_v3.py
pulumi_openstack/blockstorage/outputs.py
pulumi_openstack/blockstorage/qos_association_v3.py
pulumi_openstack/blockstorage/qos_v3.py
pulumi_openstack/blockstorage/quote_set_v3.py
pulumi_openstack/blockstorage/volume.py
pulumi_openstack/blockstorage/volume_attach.py
pulumi_openstack/blockstorage/volume_type_access_v3.py
pulumi_openstack/blockstorage/volume_type_v3.py
pulumi_openstack/compute/__init__.py
pulumi_openstack/compute/_inputs.py
pulumi_openstack/compute/aggregate_v2.py
pulumi_openstack/compute/flavor.py
pulumi_openstack/compute/flavor_access.py
pulumi_openstack/compute/get_aggregate_v2.py
pulumi_openstack/compute/get_availability_zones.py
pulumi_openstack/compute/get_flavor.py
pulumi_openstack/compute/get_hypervisor_v2.py
pulumi_openstack/compute/get_instance_v2.py
pulumi_openstack-5.4.0.dist-info/METADATA
pulumi_openstack-5.4.0.dist-info/WHEEL
pulumi_openstack-5.4.0.dist-info/top_level.txt
pulumi_openstack-5.4.0.dist-info/RECORD
